cursor_secret_scan/__init__.py
cursor_secret_scan/cli.py
cursor_secret_scan-0.1.14.dist-info/METADATA
cursor_secret_scan-0.1.14.dist-info/WHEEL
cursor_secret_scan-0.1.14.dist-info/entry_points.txt
cursor_secret_scan-0.1.14.dist-info/top_level.txt
cursor_secret_scan-0.1.14.dist-info/RECORD
